{
  "exportedBy": null,
  "bundleHash": null,
  "version": "1.0.0.0",
  "jitAssemblyCompilerCommands": [
    {
      "providerName": "CustomEntities",
      "bundleOptions": {
        "hash": "2084736515",
        "bundleName": "DeserializeJSON7e44ed",
        "entitiesBundle": {
          "Types": {
            "DeserializeJSON7e44ed": {
              "name": "DeserializeJSON7e44ed",
              "properties": [
                {
                  "name": "id",
                  "type": {
                    "ClrType": "System.Nullable`1[[System.Int32, System.Private.CoreLib]], System.Private.CoreLib"
                  },
                  "attributes": {
                    "values": [
                      {
                        "Type": {
                          "ClrType": "Newtonsoft.Json.JsonPropertyAttribute, Newtonsoft.Json"
                        },
                        "constructorArguments": [
                          {
                            "Value": "\"id\"",
                            "type": {
                              "ClrType": "System.String, System.Private.CoreLib"
                            }
                          }
                        ],
                        "namedArguments": []
                      },
                      {
                        "Type": {
                          "ClrType": "System.ComponentModel.DisplayNameAttribute, System.ComponentModel.Primitives"
                        },
                        "constructorArguments": [
                          {
                            "Value": "\"id\"",
                            "type": {
                              "ClrType": "System.String, System.Private.CoreLib"
                            }
                          }
                        ],
                        "namedArguments": []
                      }
                    ]
                  }
                },
                {
                  "name": "numero_5F_usuario",
                  "type": {
                    "ClrType": "System.String, System.Private.CoreLib"
                  },
                  "attributes": {
                    "values": [
                      {
                        "Type": {
                          "ClrType": "Newtonsoft.Json.JsonPropertyAttribute, Newtonsoft.Json"
                        },
                        "constructorArguments": [
                          {
                            "Value": "\"numero_usuario\"",
                            "type": {
                              "ClrType": "System.String, System.Private.CoreLib"
                            }
                          }
                        ],
                        "namedArguments": []
                      },
                      {
                        "Type": {
                          "ClrType": "System.ComponentModel.DisplayNameAttribute, System.ComponentModel.Primitives"
                        },
                        "constructorArguments": [
                          {
                            "Value": "\"numero_usuario\"",
                            "type": {
                              "ClrType": "System.String, System.Private.CoreLib"
                            }
                          }
                        ],
                        "namedArguments": []
                      }
                    ]
                  }
                },
                {
                  "name": "correo",
                  "type": {
                    "ClrType": "System.String, System.Private.CoreLib"
                  },
                  "attributes": {
                    "values": [
                      {
                        "Type": {
                          "ClrType": "Newtonsoft.Json.JsonPropertyAttribute, Newtonsoft.Json"
                        },
                        "constructorArguments": [
                          {
                            "Value": "\"correo\"",
                            "type": {
                              "ClrType": "System.String, System.Private.CoreLib"
                            }
                          }
                        ],
                        "namedArguments": []
                      },
                      {
                        "Type": {
                          "ClrType": "System.ComponentModel.DisplayNameAttribute, System.ComponentModel.Primitives"
                        },
                        "constructorArguments": [
                          {
                            "Value": "\"correo\"",
                            "type": {
                              "ClrType": "System.String, System.Private.CoreLib"
                            }
                          }
                        ],
                        "namedArguments": []
                      }
                    ]
                  }
                },
                {
                  "name": "plantilla_5F_usada",
                  "type": {
                    "ClrType": "System.Nullable`1[[System.Int32, System.Private.CoreLib]], System.Private.CoreLib"
                  },
                  "attributes": {
                    "values": [
                      {
                        "Type": {
                          "ClrType": "Newtonsoft.Json.JsonPropertyAttribute, Newtonsoft.Json"
                        },
                        "constructorArguments": [
                          {
                            "Value": "\"plantilla_usada\"",
                            "type": {
                              "ClrType": "System.String, System.Private.CoreLib"
                            }
                          }
                        ],
                        "namedArguments": []
                      },
                      {
                        "Type": {
                          "ClrType": "System.ComponentModel.DisplayNameAttribute, System.ComponentModel.Primitives"
                        },
                        "constructorArguments": [
                          {
                            "Value": "\"plantilla_usada\"",
                            "type": {
                              "ClrType": "System.String, System.Private.CoreLib"
                            }
                          }
                        ],
                        "namedArguments": []
                      }
                    ]
                  }
                },
                {
                  "name": "nombre_5F_plantilla",
                  "type": {
                    "ClrType": "System.String, System.Private.CoreLib"
                  },
                  "attributes": {
                    "values": [
                      {
                        "Type": {
                          "ClrType": "Newtonsoft.Json.JsonPropertyAttribute, Newtonsoft.Json"
                        },
                        "constructorArguments": [
                          {
                            "Value": "\"nombre_plantilla\"",
                            "type": {
                              "ClrType": "System.String, System.Private.CoreLib"
                            }
                          }
                        ],
                        "namedArguments": []
                      },
                      {
                        "Type": {
                          "ClrType": "System.ComponentModel.DisplayNameAttribute, System.ComponentModel.Primitives"
                        },
                        "constructorArguments": [
                          {
                            "Value": "\"nombre_plantilla\"",
                            "type": {
                              "ClrType": "System.String, System.Private.CoreLib"
                            }
                          }
                        ],
                        "namedArguments": []
                      }
                    ]
                  }
                },
                {
                  "name": "ticket_5F_creado",
                  "type": {
                    "ClrType": "System.String, System.Private.CoreLib"
                  },
                  "attributes": {
                    "values": [
                      {
                        "Type": {
                          "ClrType": "Newtonsoft.Json.JsonPropertyAttribute, Newtonsoft.Json"
                        },
                        "constructorArguments": [
                          {
                            "Value": "\"ticket_creado\"",
                            "type": {
                              "ClrType": "System.String, System.Private.CoreLib"
                            }
                          }
                        ],
                        "namedArguments": []
                      },
                      {
                        "Type": {
                          "ClrType": "System.ComponentModel.DisplayNameAttribute, System.ComponentModel.Primitives"
                        },
                        "constructorArguments": [
                          {
                            "Value": "\"ticket_creado\"",
                            "type": {
                              "ClrType": "System.String, System.Private.CoreLib"
                            }
                          }
                        ],
                        "namedArguments": []
                      }
                    ]
                  }
                },
                {
                  "name": "fecha_5F_creacion",
                  "type": {
                    "ClrType": "System.String, System.Private.CoreLib"
                  },
                  "attributes": {
                    "values": [
                      {
                        "Type": {
                          "ClrType": "Newtonsoft.Json.JsonPropertyAttribute, Newtonsoft.Json"
                        },
                        "constructorArguments": [
                          {
                            "Value": "\"fecha_creacion\"",
                            "type": {
                              "ClrType": "System.String, System.Private.CoreLib"
                            }
                          }
                        ],
                        "namedArguments": []
                      },
                      {
                        "Type": {
                          "ClrType": "System.ComponentModel.DisplayNameAttribute, System.ComponentModel.Primitives"
                        },
                        "constructorArguments": [
                          {
                            "Value": "\"fecha_creacion\"",
                            "type": {
                              "ClrType": "System.String, System.Private.CoreLib"
                            }
                          }
                        ],
                        "namedArguments": []
                      }
                    ]
                  }
                },
                {
                  "name": "status_5F_proceso",
                  "type": {
                    "ClrType": "System.String, System.Private.CoreLib"
                  },
                  "attributes": {
                    "values": [
                      {
                        "Type": {
                          "ClrType": "Newtonsoft.Json.JsonPropertyAttribute, Newtonsoft.Json"
                        },
                        "constructorArguments": [
                          {
                            "Value": "\"status_proceso\"",
                            "type": {
                              "ClrType": "System.String, System.Private.CoreLib"
                            }
                          }
                        ],
                        "namedArguments": []
                      },
                      {
                        "Type": {
                          "ClrType": "System.ComponentModel.DisplayNameAttribute, System.ComponentModel.Primitives"
                        },
                        "constructorArguments": [
                          {
                            "Value": "\"status_proceso\"",
                            "type": {
                              "ClrType": "System.String, System.Private.CoreLib"
                            }
                          }
                        ],
                        "namedArguments": []
                      }
                    ]
                  }
                },
                {
                  "name": "error_5F_detalle",
                  "type": {
                    "ClrType": "System.Object, System.Private.CoreLib"
                  },
                  "attributes": {
                    "values": [
                      {
                        "Type": {
                          "ClrType": "Newtonsoft.Json.JsonPropertyAttribute, Newtonsoft.Json"
                        },
                        "constructorArguments": [
                          {
                            "Value": "\"error_detalle\"",
                            "type": {
                              "ClrType": "System.String, System.Private.CoreLib"
                            }
                          }
                        ],
                        "namedArguments": []
                      },
                      {
                        "Type": {
                          "ClrType": "System.ComponentModel.DisplayNameAttribute, System.ComponentModel.Primitives"
                        },
                        "constructorArguments": [
                          {
                            "Value": "\"error_detalle\"",
                            "type": {
                              "ClrType": "System.String, System.Private.CoreLib"
                            }
                          }
                        ],
                        "namedArguments": []
                      }
                    ]
                  }
                },
                {
                  "name": "tipo_5F_solicitud",
                  "type": {
                    "ClrType": "System.String, System.Private.CoreLib"
                  },
                  "attributes": {
                    "values": [
                      {
                        "Type": {
                          "ClrType": "Newtonsoft.Json.JsonPropertyAttribute, Newtonsoft.Json"
                        },
                        "constructorArguments": [
                          {
                            "Value": "\"tipo_solicitud\"",
                            "type": {
                              "ClrType": "System.String, System.Private.CoreLib"
                            }
                          }
                        ],
                        "namedArguments": []
                      },
                      {
                        "Type": {
                          "ClrType": "System.ComponentModel.DisplayNameAttribute, System.ComponentModel.Primitives"
                        },
                        "constructorArguments": [
                          {
                            "Value": "\"tipo_solicitud\"",
                            "type": {
                              "ClrType": "System.String, System.Private.CoreLib"
                            }
                          }
                        ],
                        "namedArguments": []
                      }
                    ]
                  }
                },
                {
                  "name": "password_5F_temporal",
                  "type": {
                    "ClrType": "System.String, System.Private.CoreLib"
                  },
                  "attributes": {
                    "values": [
                      {
                        "Type": {
                          "ClrType": "Newtonsoft.Json.JsonPropertyAttribute, Newtonsoft.Json"
                        },
                        "constructorArguments": [
                          {
                            "Value": "\"password_temporal\"",
                            "type": {
                              "ClrType": "System.String, System.Private.CoreLib"
                            }
                          }
                        ],
                        "namedArguments": []
                      },
                      {
                        "Type": {
                          "ClrType": "System.ComponentModel.DisplayNameAttribute, System.ComponentModel.Primitives"
                        },
                        "constructorArguments": [
                          {
                            "Value": "\"password_temporal\"",
                            "type": {
                              "ClrType": "System.String, System.Private.CoreLib"
                            }
                          }
                        ],
                        "namedArguments": []
                      }
                    ]
                  }
                },
                {
                  "name": "canal",
                  "type": {
                    "ClrType": "System.String, System.Private.CoreLib"
                  },
                  "attributes": {
                    "values": [
                      {
                        "Type": {
                          "ClrType": "Newtonsoft.Json.JsonPropertyAttribute, Newtonsoft.Json"
                        },
                        "constructorArguments": [
                          {
                            "Value": "\"canal\"",
                            "type": {
                              "ClrType": "System.String, System.Private.CoreLib"
                            }
                          }
                        ],
                        "namedArguments": []
                      },
                      {
                        "Type": {
                          "ClrType": "System.ComponentModel.DisplayNameAttribute, System.ComponentModel.Primitives"
                        },
                        "constructorArguments": [
                          {
                            "Value": "\"canal\"",
                            "type": {
                              "ClrType": "System.String, System.Private.CoreLib"
                            }
                          }
                        ],
                        "namedArguments": []
                      }
                    ]
                  }
                },
                {
                  "name": "pw_5F_rpa",
                  "type": {
                    "ClrType": "System.String, System.Private.CoreLib"
                  },
                  "attributes": {
                    "values": [
                      {
                        "Type": {
                          "ClrType": "Newtonsoft.Json.JsonPropertyAttribute, Newtonsoft.Json"
                        },
                        "constructorArguments": [
                          {
                            "Value": "\"pw_rpa\"",
                            "type": {
                              "ClrType": "System.String, System.Private.CoreLib"
                            }
                          }
                        ],
                        "namedArguments": []
                      },
                      {
                        "Type": {
                          "ClrType": "System.ComponentModel.DisplayNameAttribute, System.ComponentModel.Primitives"
                        },
                        "constructorArguments": [
                          {
                            "Value": "\"pw_rpa\"",
                            "type": {
                              "ClrType": "System.String, System.Private.CoreLib"
                            }
                          }
                        ],
                        "namedArguments": []
                      }
                    ]
                  }
                }
              ],
              "values": [],
              "baseType": null
            }
          },
          "Metadata": {},
          "version": 1
        }
      },
      "entityAssemblyKey": {
        "name": "UiPath.Web.Activities.ViewModels.SWEntities.DeserializeJSON7e44ed",
        "hash": "MjA4NDczNjUxNQ",
        "assemblyName": "DeserializeJSON7e44e.NXIaZ1zTdJD1VMQ4I2HjR7K1"
      }
    }
  ]
}